viterbi/viterbi.v
module viterbi(CLK, RST, valid_i, data_i, valid_o, data_o);
   input       CLK, RST, valid_i;
   input [1:0] data_i;
   output      valid_o, data_o;

   reg [1:0]   select;
   reg [5:0]   count;
   
   wire        valid_i_0, valid_i_1, valid_i_2, valid_i_3;
   wire        valid_o_0, valid_o_1, valid_o_2, valid_o_3;
   wire        data_o_0, data_o_1, data_o_2, data_o_3;
   
   always @(posedge CLK or negedge RST) begin
      if (RST == 1'b0) begin
	 select <= 2'd0;
	 count <= 6'd0;
      end else begin
	 if (valid_i == 1'b1) begin
	    count <= count + 6'd1;
	 end
	 if (count == 6'd63) begin
	    select <= select + 2'd1;
	 end
      end
   end

   assign valid_i_0 = (valid_i == 1'b1 && select == 2'd0) ? 1'b1 : 1'b0;
   assign valid_i_1 = (valid_i == 1'b1 && select == 2'd1) ? 1'b1 : 1'b0;
   assign valid_i_2 = (valid_i == 1'b1 && select == 2'd2) ? 1'b1 : 1'b0;
   assign valid_i_3 = (valid_i == 1'b1 && select == 2'd3) ? 1'b1 : 1'b0;
   assign valid_o = valid_o_0 | valid_o_1 | valid_o_2 | valid_o_3;
   assign data_o = (valid_o_0 == 1'b1) ? data_o_0 : ((valid_o_1 == 1'b1) ? data_o_1 : ((valid_o_2 == 1'b1) ? data_o_2 : data_o_3));

   execute execute0(CLK, RST, valid_i_0, data_i, valid_o_0, data_o_0);
   execute execute1(CLK, RST, valid_i_1, data_i, valid_o_1, data_o_1);
   execute execute2(CLK, RST, valid_i_2, data_i, valid_o_2, data_o_2);
   execute execute3(CLK, RST, valid_i_3, data_i, valid_o_3, data_o_3);
endmodule
  
module execute(CLK, RST, valid_i, data_i, valid_o, data_o);
   input       CLK, RST, valid_i;
   input [1:0] data_i;
   output reg  valid_o, data_o;

   reg 	       working;
   reg [31:0]  count, sum00, sum01, sum10, sum11;
   reg [1:0]   pre00[0:63], pre01[0:63], pre10[0:63], pre11[0:63];
   reg [1:0]   state;
   reg [63:0]  data;
   
   always @(posedge CLK or negedge RST) begin
      if (RST == 1'b0) begin
	 working <= 1'b0;
	 count <= 32'd0;
	 valid_o <= 1'b0;
	 sum00 <= 32'd0;
	 sum01 <= 32'd0;
	 sum10 <= 32'd0;
	 sum11 <= 32'd0;
      end else begin
	 if (valid_i == 1'b1) begin
	    working <= 1'b1;
	 end
	 if (valid_i == 1'b1 || working == 1'b1) begin
	    if (count == 0) begin
	       sum00 <= sum00 +  data_i[0] +  data_i[1];
	       sum10 <= sum00 + {31'd0, ~data_i[0]} + {31'd0, ~data_i[1]};
	       pre00[count] <= 2'b00;
	       pre10[count] <= 2'b00;
	       count <= count + 32'd1;
	    end else if (count == 1) begin
	       sum00 <= sum00 + {31'd0,  data_i[0]} + {31'd0,  data_i[1]};
	       sum01 <= sum10 + {31'd0,  data_i[0]} + {31'd0, ~data_i[1]};
	       sum10 <= sum00 + {31'd0, ~data_i[0]} + {31'd0, ~data_i[1]};
  	       sum11 <= sum10 + {31'd0, ~data_i[0]} + {31'd0,  data_i[1]};
	       pre00[count] <= 2'b00;
	       pre01[count] <= 2'b10;
	       pre10[count] <= 2'b00;
	       pre11[count] <= 2'b10;
	       count <= count + 32'd1;
	    end else if (count >= 2 && count <= 63) begin
	       sum00 <= (sum00 + {31'd0,  data_i[0]} + {31'd0,  data_i[1]} < sum01 + {31'd0, ~data_i[0]} + {31'd0, ~data_i[1]}) ? sum00 + {31'd0,  data_i[0]} + {31'd0,  data_i[1]} : sum01 + {31'd0, ~data_i[0]} + {31'd0, ~data_i[1]};
	       sum01 <= (sum10 + {31'd0,  data_i[0]} + {31'd0, ~data_i[1]} < sum11 + {31'd0, ~data_i[0]} + {31'd0,  data_i[1]}) ? sum10 + {31'd0,  data_i[0]} + {31'd0, ~data_i[1]} : sum11 + {31'd0, ~data_i[0]} + {31'd0,  data_i[1]};
	       sum10 <= (sum00 + {31'd0, ~data_i[0]} + {31'd0, ~data_i[1]} < sum01 + {31'd0,  data_i[0]} + {31'd0,  data_i[1]}) ? sum00 + {31'd0, ~data_i[0]} + {31'd0, ~data_i[1]} : sum01 + {31'd0,  data_i[0]} + {31'd0,  data_i[1]};
  	       sum11 <= (sum10 + {31'd0, ~data_i[0]} + {31'd0,  data_i[1]} < sum11 + {31'd0,  data_i[0]} + {31'd0, ~data_i[1]}) ? sum10 + {31'd0, ~data_i[0]} + {31'd0,  data_i[1]} : sum11 + {31'd0,  data_i[0]} + {31'd0, ~data_i[1]};
	       pre00[count] <= (sum00 + {31'd0,  data_i[0]} + {31'd0,  data_i[1]} < sum01 + {31'd0, ~data_i[0]} + {31'd0, ~data_i[1]}) ? 2'b00 : 2'b01;
	       pre01[count] <= (sum10 + {31'd0,  data_i[0]} + {31'd0, ~data_i[1]} < sum11 + {31'd0, ~data_i[0]} + {31'd0,  data_i[1]}) ? 2'b10 : 2'b11;
	       pre10[count] <= (sum00 + {31'd0, ~data_i[0]} + {31'd0, ~data_i[1]} < sum01 + {31'd0,  data_i[0]} + {31'd0,  data_i[1]}) ? 2'b00 : 2'b01;
	       pre11[count] <= (sum10 + {31'd0, ~data_i[0]} + {31'd0,  data_i[1]} < sum11 + {31'd0,  data_i[0]} + {31'd0, ~data_i[1]}) ? 2'b10 : 2'b11;
	       count <= count + 32'd1;
	    end else if (count == 64) begin
	       state <= min(sum00, sum01, sum10, sum11);
	       count <= count + 32'd1;
	    end else if (count >= 65 && count <= 128) begin
	       data[128 - count] <= (state == 2'b00 || state == 2'b01) ? 0 : 1;
	       state <= (state == 2'b00) ? pre00[128 - count] : ((state == 2'b01) ? pre01[128 - count] : ((state == 2'b10) ? pre10[128 - count] : pre11[128 - count]));
	       count <= count + 32'd1;
	    end	else if (count >= 129 && count <= 192) begin
	       valid_o <= 1'b1;
	       data_o <= data[count - 129];
	       count <= count + 32'd1;
	    end else if (count == 193) begin
	       working <= 1'b0;
	       count <= 32'd0;
	       valid_o <= 1'b0;
	       sum00 <= 32'd0;
	       sum01 <= 32'd0;
	       sum10 <= 32'd0;
	       sum11 <= 32'd0;
	    end
	 end
      end
   end

   function [1:0] min;
      input [31:0] sum00, sum01, sum10, sum11;
      begin
	 if (sum00 <= sum01 && sum01 <= sum10 && sum10 <= sum11) min = 2'b00;
	 else if (sum00 <= sum01 && sum01 <= sum11 && sum11 <= sum10) min = 2'b00;
	 else if (sum00 <= sum10 && sum10 <= sum01 && sum01 <= sum11) min = 2'b00;
	 else if (sum00 <= sum10 && sum10 <= sum11 && sum11 <= sum01) min = 2'b00;
	 else if (sum00 <= sum11 && sum11 <= sum01 && sum01 <= sum10) min = 2'b00;
	 else if (sum00 <= sum11 && sum11 <= sum10 && sum10 <= sum01) min = 2'b00;

	 else if (sum01 <= sum00 && sum00 <= sum10 && sum10 <= sum11) min = 2'b01;
	 else if (sum01 <= sum00 && sum00 <= sum11 && sum11 <= sum10) min = 2'b01;
	 else if (sum01 <= sum10 && sum10 <= sum00 && sum00 <= sum11) min = 2'b01;
	 else if (sum01 <= sum10 && sum10 <= sum11 && sum11 <= sum00) min = 2'b01;
	 else if (sum01 <= sum11 && sum11 <= sum00 && sum00 <= sum10) min = 2'b01;
	 else if (sum01 <= sum11 && sum11 <= sum10 && sum10 <= sum00) min = 2'b01;      

	 else if (sum10 <= sum00 && sum00 <= sum01 && sum01 <= sum11) min = 2'b10;
	 else if (sum10 <= sum00 && sum00 <= sum11 && sum11 <= sum01) min = 2'b10;
	 else if (sum10 <= sum01 && sum01 <= sum00 && sum00 <= sum11) min = 2'b10;
	 else if (sum10 <= sum01 && sum01 <= sum11 && sum11 <= sum00) min = 2'b10;
	 else if (sum10 <= sum11 && sum11 <= sum00 && sum00 <= sum01) min = 2'b10;
	 else if (sum10 <= sum11 && sum11 <= sum01 && sum01 <= sum00) min = 2'b10;

	 else if (sum11 <= sum00 && sum00 <= sum01 && sum01 <= sum10) min = 2'b11;
	 else if (sum11 <= sum00 && sum00 <= sum10 && sum10 <= sum01) min = 2'b11;
	 else if (sum11 <= sum01 && sum01 <= sum00 && sum00 <= sum10) min = 2'b11;
	 else if (sum11 <= sum01 && sum01 <= sum10 && sum00 <= sum00) min = 2'b11;
	 else if (sum11 <= sum10 && sum10 <= sum00 && sum00 <= sum01) min = 2'b11;
	 else if (sum11 <= sum10 && sum10 <= sum01 && sum01 <= sum00) min = 2'b11;
      end
   endfunction
endmodule

viterbi/convolution.v
module convolution(CLK, RST, valid_i, data_i, valid_o, data_o);
   input 	    CLK, RST, valid_i, data_i;
   output reg 	    valid_o;
   output reg [1:0] data_o;

   reg 		    d1, d2;
   reg [5:0] 	    count;
   
   always @(posedge CLK or negedge RST) begin
      if (RST == 1'b0) begin
	 count <= 6'd0;
	 d1 <= 1'b0;
	 d2 <= 1'b0;
	 valid_o <= 1'b0;
      end else begin
	 valid_o <= valid_i;
	 data_o[0] <= data_i ^ d2;
	 data_o[1] <= data_i ^ d1 ^ d2;
	 if (count != 6'd63 && valid_i == 1'b1) begin
	    count <= count + 6'd1;
	    d1 <= data_i;
	    d2 <= d1;
	 end else if (count == 6'd63 && valid_i == 1'b1) begin
	    count <= 6'd0;
	    d1 <= 1'b0;
	    d2 <= 1'b0;
	 end
      end
   end
endmodule

viterbi/viterbisim.v
module viterbisim;
   reg CLK, RST, valid_i, data_i;
   wire valid_e;
   wire [1:0] data_e;
   wire       valid_d, data_d;
   wire signed [63:0] data;
   integer    i, error;
   
   convolution convolution(CLK, RST, valid_i, data_i, valid_e, data_e);
   viterbi viterbi(CLK, RST, valid_e, data_e, valid_d, data_d);

   initial begin
      $dumpfile("viterbi.vcd");
      $dumpvars(0, viterbisim);
      CLK <= 1'b1;
      RST <= 1'b1;
      valid_i <= 1'b0;
      #10 RST <= 1'b0;
      #10 RST <= 1'b1;

      for (i = 0; i < 64; i = i + 1) begin
	 #10;
	 valid_i <= 1'b1;
	 data_i <= data[i];
      end

      #10 valid_i <= 1'b0;

      $write("send\t");
      for (i = 0; i < 64; i = i + 1) begin
	 $write("%b", data[i]);
      end
      $write("\n");
      
      $write("receive\t");
      i = 0;
      error = 0;
      while (i < 64) begin
	 #10;
	 if (valid_d == 1'b1) begin
	    $write("%b", data_d);
	    if (data_d != data[i]) error = error + 1;
	    i = i + 1;
	 end
      end
      $write("\n");

      $write("error\t%1d\n", error);

      #10 valid_i <= 1'b0;

      #10000 $finish;
   end

   always begin
      #5 CLK = ~CLK;
   end
      
   assign data[0] = 1'b0;
   assign data[1] = 1'b1;
   assign data[2] = 1'b0;
   assign data[3] = 1'b0;
   assign data[4] = 1'b1;
   assign data[5] = 1'b0;
   assign data[6] = 1'b0;
   assign data[7] = 1'b1;
   assign data[8] = 1'b0;
   assign data[9] = 1'b0;
   assign data[10] = 1'b1;
   assign data[11] = 1'b0;
   assign data[12] = 1'b0;
   assign data[13] = 1'b1;
   assign data[14] = 1'b0;
   assign data[15] = 1'b0;
   assign data[16] = 1'b1;
   assign data[17] = 1'b0;
   assign data[18] = 1'b0;
   assign data[19] = 1'b1;
   assign data[20] = 1'b0;
   assign data[21] = 1'b0;
   assign data[22] = 1'b1;
   assign data[23] = 1'b0;
   assign data[24] = 1'b0;
   assign data[25] = 1'b1;
   assign data[26] = 1'b0;
   assign data[27] = 1'b0;
   assign data[28] = 1'b1;
   assign data[29] = 1'b0;
   assign data[30] = 1'b0;
   assign data[31] = 1'b1;
   assign data[32] = 1'b0;
   assign data[33] = 1'b0;
   assign data[34] = 1'b1;
   assign data[35] = 1'b0;
   assign data[36] = 1'b0;
   assign data[37] = 1'b1;
   assign data[38] = 1'b0;
   assign data[39] = 1'b0;
   assign data[40] = 1'b1;
   assign data[41] = 1'b0;
   assign data[42] = 1'b0;
   assign data[43] = 1'b1;
   assign data[44] = 1'b0;
   assign data[45] = 1'b0;
   assign data[46] = 1'b1;
   assign data[47] = 1'b0;
   assign data[48] = 1'b0;
   assign data[49] = 1'b1;
   assign data[50] = 1'b0;
   assign data[50] = 1'b0;
   assign data[51] = 1'b1;
   assign data[52] = 1'b0;
   assign data[53] = 1'b0;
   assign data[54] = 1'b0;
   assign data[55] = 1'b1;
   assign data[56] = 1'b0;
   assign data[57] = 1'b0;
   assign data[58] = 1'b1;
   assign data[59] = 1'b0;
   assign data[60] = 1'b0;
   assign data[61] = 1'b1;
   assign data[62] = 1'b0;
   assign data[63] = 1'b0;
endmodule

viterbi/viterbi.vcd
$date
	Tue Jan 13 11:29:45 2015
$end
$version
	Icarus Verilog
$end
$timescale
	1s
$end
$scope module viterbisim $end
$var wire 64 ! data [63:0] $end
$var wire 1 " data_d $end
$var wire 2 # data_e [1:0] $end
$var wire 1 $ valid_d $end
$var wire 1 % valid_e $end
$var reg 1 & CLK $end
$var reg 1 ' RST $end
$var reg 1 ( data_i $end
$var integer 32 ) error [31:0] $end
$var integer 32 * i [31:0] $end
$var reg 1 + valid_i $end
$scope module convolution $end
$var wire 1 , CLK $end
$var wire 1 - RST $end
$var wire 1 . data_i $end
$var wire 1 / valid_i $end
$var reg 6 0 count [5:0] $end
$var reg 1 1 d1 $end
$var reg 1 2 d2 $end
$var reg 2 3 data_o [1:0] $end
$var reg 1 4 valid_o $end
$upscope $end
$scope module viterbi $end
$var wire 1 , CLK $end
$var wire 1 - RST $end
$var wire 2 5 data_i [1:0] $end
$var wire 1 " data_o $end
$var wire 1 6 data_o_0 $end
$var wire 1 7 data_o_1 $end
$var wire 1 8 data_o_2 $end
$var wire 1 9 data_o_3 $end
$var wire 1 % valid_i $end
$var wire 1 : valid_i_0 $end
$var wire 1 ; valid_i_1 $end
$var wire 1 < valid_i_2 $end
$var wire 1 = valid_i_3 $end
$var wire 1 $ valid_o $end
$var wire 1 > valid_o_0 $end
$var wire 1 ? valid_o_1 $end
$var wire 1 @ valid_o_2 $end
$var wire 1 A valid_o_3 $end
$var reg 6 B count [5:0] $end
$var reg 2 C select [1:0] $end
$scope module execute0 $end
$var wire 1 , CLK $end
$var wire 1 - RST $end
$var wire 2 D data_i [1:0] $end
$var wire 1 : valid_i $end
$var reg 32 E count [31:0] $end
$var reg 64 F data [63:0] $end
$var reg 1 G data_o $end
$var reg 2 H state [1:0] $end
$var reg 32 I sum00 [31:0] $end
$var reg 32 J sum01 [31:0] $end
$var reg 32 K sum10 [31:0] $end
$var reg 32 L sum11 [31:0] $end
$var reg 1 M valid_o $end
$var reg 1 N working $end
$scope function min $end
$var reg 2 O min [1:0] $end
$var reg 32 P sum00 [31:0] $end
$var reg 32 Q sum01 [31:0] $end
$var reg 32 R sum10 [31:0] $end
$var reg 32 S sum11 [31:0] $end
$upscope $end
$upscope $end
$scope module execute1 $end
$var wire 1 , CLK $end
$var wire 1 - RST $end
$var wire 2 T data_i [1:0] $end
$var wire 1 ; valid_i $end
$var reg 32 U count [31:0] $end
$var reg 64 V data [63:0] $end
$var reg 1 W data_o $end
$var reg 2 X state [1:0] $end
$var reg 32 Y sum00 [31:0] $end
$var reg 32 Z sum01 [31:0] $end
$var reg 32 [ sum10 [31:0] $end
$var reg 32 \ sum11 [31:0] $end
$var reg 1 ] valid_o $end
$var reg 1 ^ working $end
$scope function min $end
$var reg 2 _ min [1:0] $end
$var reg 32 ` sum00 [31:0] $end
$var reg 32 a sum01 [31:0] $end
$var reg 32 b sum10 [31:0] $end
$var reg 32 c sum11 [31:0] $end
$upscope $end
$upscope $end
$scope module execute2 $end
$var wire 1 , CLK $end
$var wire 1 - RST $end
$var wire 2 d data_i [1:0] $end
$var wire 1 < valid_i $end
$var reg 32 e count [31:0] $end
$var reg 64 f data [63:0] $end
$var reg 1 g data_o $end
$var reg 2 h state [1:0] $end
$var reg 32 i sum00 [31:0] $end
$var reg 32 j sum01 [31:0] $end
$var reg 32 k sum10 [31:0] $end
$var reg 32 l sum11 [31:0] $end
$var reg 1 m valid_o $end
$var reg 1 n working $end
$scope function min $end
$var reg 2 o min [1:0] $end
$var reg 32 p sum00 [31:0] $end
$var reg 32 q sum01 [31:0] $end
$var reg 32 r sum10 [31:0] $end
$var reg 32 s sum11 [31:0] $end
$upscope $end
$upscope $end
$scope module execute3 $end
$var wire 1 , CLK $end
$var wire 1 - RST $end
$var wire 2 t data_i [1:0] $end
$var wire 1 = valid_i $end
$var reg 32 u count [31:0] $end
$var reg 64 v data [63:0] $end
$var reg 1 w data_o $end
$var reg 2 x state [1:0] $end
$var reg 32 y sum00 [31:0] $end
$var reg 32 z sum01 [31:0] $end
$var reg 32 { sum10 [31:0] $end
$var reg 32 | sum11 [31:0] $end
$var reg 1 } valid_o $end
$var reg 1 ~ working $end
$scope function min $end
$var reg 2 !" min [1:0] $end
$var reg 32 "" sum00 [31:0] $end
$var reg 32 #" sum01 [31:0] $end
$var reg 32 $" sum10 [31:0] $end
$var reg 32 %" sum11 [31:0] $end
$upscope $end
$upscope $end
$upscope $end
$upscope $end
$enddefinitions $end
#0
$dumpvars
bx %"
bx $"
bx #"
bx ""
bx !"
x~
x}
bx |
bx {
bx z
bx y
bx x
xw
bx v
bx u
bx t
bx s
bx r
bx q
bx p
bx o
xn
xm
bx l
bx k
bx j
bx i
bx h
xg
bx f
bx e
bx d
bx c
bx b
bx a
bx `
bx _
x^
x]
bx \
bx [
bx Z
bx Y
bx X
xW
bx V
bx U
bx T
bx S
bx R
bx Q
bx P
bx O
xN
xM
bx L
bx K
bx J
bx I
bx H
xG
bx F
bx E
bx D
bx C
bx B
xA
x@
x?
x>
0=
0<
0;
0:
x9
x8
x7
x6
bx 5
04
bx 3
x2
x1
bx 0
0/
x.
1-
1,
0+
bx *
bx )
x(
1'
1&
0%
x$
bx #
x"
b10010010001010010010010010010010010010010010010010010010010010 !
$end
#5
0&
0,
#10
0$
02
01
b0 0
b0 L
b0 K
b0 J
b0 I
0M
0>
b0 E
0N
b0 \
b0 [
b0 Z
b0 Y
0]
0?
b0 U
0^
b0 l
b0 k
b0 j
b0 i
0m
0@
b0 e
0n
b0 |
b0 {
b0 z
b0 y
0}
0A
b0 u
0~
b0 B
b0 C
bx 3
0'
0-
1&
1,
#15
0&
0,
#20
1'
1-
1&
1,
b0 *
#25
0&
0,
#30
bx 3
0(
0.
1+
1/
1&
1,
b1 *
#35
0&
0,
#40
1:
b1 0
b0 3
b0 #
b0 5
b0 D
b0 T
b0 d
b0 t
14
1%
1(
1.
1&
1,
b10 *
#45
0&
0,
#50
11
b10 0
b11 3
b11 #
b11 5
b11 D
b11 T
b11 d
b11 t
b1 E
b10 K
1N
b1 B
0(
0.
1&
1,
b11 *
#55
0&
0,
#60
b10 B
b10 E
b11 L
b0 K
b11 J
b10 I
12
01
b11 0
b10 3
b10 #
b10 5
b10 D
b10 T
b10 d
b10 t
1&
1,
b100 *
#65
0&
0,
#70
02
b100 0
b11 3
b11 #
b11 5
b11 D
b11 T
b11 d
b11 t
b11 E
b10 L
b11 K
b0 J
b11 I
b11 B
1(
1.
1&
1,
b101 *
#75
0&
0,
#80
b100 B
b100 E
b11 L
b10 K
b11 J
b0 I
11
b101 0
b11 3
0(
0.
1&
1,
b110 *
#85
0&
0,
#90
12
01
b110 0
b10 3
b10 #
b10 5
b10 D
b10 T
b10 d
b10 t
b101 E
b0 K
b10 I
b101 B
1&
1,
b111 *
#95
0&
0,
#100
b110 B
b110 E
b10 L
b11 K
b0 J
b11 I
02
b111 0
b11 3
b11 #
b11 5
b11 D
b11 T
b11 d
b11 t
1(
1.
1&
1,
b1000 *
#105
0&
0,
#110
11
b1000 0
b11 3
b111 E
b11 L
b10 K
b11 J
b0 I
b111 B
0(
0.
1&
1,
b1001 *
#115
0&
0,
#120
b1000 B
b1000 E
b0 K
b10 I
12
01
b1001 0
b10 3
b10 #
b10 5
b10 D
b10 T
b10 d
b10 t
1&
1,
b1010 *
#125
0&
0,
#130
02
b1010 0
b11 3
b11 #
b11 5
b11 D
b11 T
b11 d
b11 t
b1001 E
b10 L
b11 K
b0 J
b11 I
b1001 B
1(
1.
1&
1,
b1011 *
#135
0&
0,
#140
b1010 B
b1010 E
b11 L
b10 K
b11 J
b0 I
11
b1011 0
b11 3
0(
0.
1&
1,
b1100 *
#145
0&
0,
#150
12
01
b1100 0
b10 3
b10 #
b10 5
b10 D
b10 T
b10 d
b10 t
b1011 E
b0 K
b10 I
b1011 B
1&
1,
b1101 *
#155
0&
0,
#160
b1100 B
b1100 E
b10 L
b11 K
b0 J
b11 I
02
b1101 0
b11 3
b11 #
b11 5
b11 D
b11 T
b11 d
b11 t
1(
1.
1&
1,
b1110 *
#165
0&
0,
#170
11
b1110 0
b11 3
b1101 E
b11 L
b10 K
b11 J
b0 I
b1101 B
0(
0.
1&
1,
b1111 *
#175
0&
0,
#180
b1110 B
b1110 E
b0 K
b10 I
12
01
b1111 0
b10 3
b10 #
b10 5
b10 D
b10 T
b10 d
b10 t
1&
1,
b10000 *
#185
0&
0,
#190
02
b10000 0
b11 3
b11 #
b11 5
b11 D
b11 T
b11 d
b11 t
b1111 E
b10 L
b11 K
b0 J
b11 I
b1111 B
1(
1.
1&
1,
b10001 *
#195
0&
0,
#200
b10000 B
b10000 E
b11 L
b10 K
b11 J
b0 I
11
b10001 0
b11 3
0(
0.
1&
1,
b10010 *
#205
0&
0,
#210
12
01
b10010 0
b10 3
b10 #
b10 5
b10 D
b10 T
b10 d
b10 t
b10001 E
b0 K
b10 I
b10001 B
1&
1,
b10011 *
#215
0&
0,
#220
b10010 B
b10010 E
b10 L
b11 K
b0 J
b11 I
02
b10011 0
b11 3
b11 #
b11 5
b11 D
b11 T
b11 d
b11 t
1(
1.
1&
1,
b10100 *
#225
0&
0,
#230
11
b10100 0
b11 3
b10011 E
b11 L
b10 K
b11 J
b0 I
b10011 B
0(
0.
1&
1,
b10101 *
#235
0&
0,
#240
b10100 B
b10100 E
b0 K
b10 I
12
01
b10101 0
b10 3
b10 #
b10 5
b10 D
b10 T
b10 d
b10 t
1&
1,
b10110 *
#245
0&
0,
#250
02
b10110 0
b11 3
b11 #
b11 5
b11 D
b11 T
b11 d
b11 t
b10101 E
b10 L
b11 K
b0 J
b11 I
b10101 B
1(
1.
1&
1,
b10111 *
#255
0&
0,
#260
b10110 B
b10110 E
b11 L
b10 K
b11 J
b0 I
11
b10111 0
b11 3
0(
0.
1&
1,
b11000 *
#265
0&
0,
#270
12
01
b11000 0
b10 3
b10 #
b10 5
b10 D
b10 T
b10 d
b10 t
b10111 E
b0 K
b10 I
b10111 B
1&
1,
b11001 *
#275
0&
0,
#280
b11000 B
b11000 E
b10 L
b11 K
b0 J
b11 I
02
b11001 0
b11 3
b11 #
b11 5
b11 D
b11 T
b11 d
b11 t
1(
1.
1&
1,
b11010 *
#285
0&
0,
#290
11
b11010 0
b11 3
b11001 E
b11 L
b10 K
b11 J
b0 I
b11001 B
0(
0.
1&
1,
b11011 *
#295
0&
0,
#300
b11010 B
b11010 E
b0 K
b10 I
12
01
b11011 0
b10 3
b10 #
b10 5
b10 D
b10 T
b10 d
b10 t
1&
1,
b11100 *
#305
0&
0,
#310
02
b11100 0
b11 3
b11 #
b11 5
b11 D
b11 T
b11 d
b11 t
b11011 E
b10 L
b11 K
b0 J
b11 I
b11011 B
1(
1.
1&
1,
b11101 *
#315
0&
0,
#320
b11100 B
b11100 E
b11 L
b10 K
b11 J
b0 I
11
b11101 0
b11 3
0(
0.
1&
1,
b11110 *
#325
0&
0,
#330
12
01
b11110 0
b10 3
b10 #
b10 5
b10 D
b10 T
b10 d
b10 t
b11101 E
b0 K
b10 I
b11101 B
1&
1,
b11111 *
#335
0&
0,
#340
b11110 B
b11110 E
b10 L
b11 K
b0 J
b11 I
02
b11111 0
b11 3
b11 #
b11 5
b11 D
b11 T
b11 d
b11 t
1(
1.
1&
1,
b100000 *
#345
0&
0,
#350
11
b100000 0
b11 3
b11111 E
b11 L
b10 K
b11 J
b0 I
b11111 B
0(
0.
1&
1,
b100001 *
#355
0&
0,
#360
b100000 B
b100000 E
b0 K
b10 I
12
01
b100001 0
b10 3
b10 #
b10 5
b10 D
b10 T
b10 d
b10 t
1&
1,
b100010 *
#365
0&
0,
#370
02
b100010 0
b11 3
b11 #
b11 5
b11 D
b11 T
b11 d
b11 t
b100001 E
b10 L
b11 K
b0 J
b11 I
b100001 B
1(
1.
1&
1,
b100011 *
#375
0&
0,
#380
b100010 B
b100010 E
b11 L
b10 K
b11 J
b0 I
11
b100011 0
b11 3
0(
0.
1&
1,
b100100 *
#385
0&
0,
#390
12
01
b100100 0
b10 3
b10 #
b10 5
b10 D
b10 T
b10 d
b10 t
b100011 E
b0 K
b10 I
b100011 B
1&
1,
b100101 *
#395
0&
0,
#400
b100100 B
b100100 E
b10 L
b11 K
b0 J
b11 I
02
b100101 0
b11 3
b11 #
b11 5
b11 D
b11 T
b11 d
b11 t
1(
1.
1&
1,
b100110 *
#405
0&
0,
#410
11
b100110 0
b11 3
b100101 E
b11 L
b10 K
b11 J
b0 I
b100101 B
0(
0.
1&
1,
b100111 *
#415
0&
0,
#420
b100110 B
b100110 E
b0 K
b10 I
12
01
b100111 0
b10 3
b10 #
b10 5
b10 D
b10 T
b10 d
b10 t
1&
1,
b101000 *
#425
0&
0,
#430
02
b101000 0
b11 3
b11 #
b11 5
b11 D
b11 T
b11 d
b11 t
b100111 E
b10 L
b11 K
b0 J
b11 I
b100111 B
1(
1.
1&
1,
b101001 *
#435
0&
0,
#440
b101000 B
b101000 E
b11 L
b10 K
b11 J
b0 I
11
b101001 0
b11 3
0(
0.
1&
1,
b101010 *
#445
0&
0,
#450
12
01
b101010 0
b10 3
b10 #
b10 5
b10 D
b10 T
b10 d
b10 t
b101001 E
b0 K
b10 I
b101001 B
1&
1,
b101011 *
#455
0&
0,
#460
b101010 B
b101010 E
b10 L
b11 K
b0 J
b11 I
02
b101011 0
b11 3
b11 #
b11 5
b11 D
b11 T
b11 d
b11 t
1(
1.
1&
1,
b101100 *
#465
0&
0,
#470
11
b101100 0
b11 3
b101011 E
b11 L
b10 K
b11 J
b0 I
b101011 B
0(
0.
1&
1,
b101101 *
#475
0&
0,
#480
b101100 B
b101100 E
b0 K
b10 I
12
01
b101101 0
b10 3
b10 #
b10 5
b10 D
b10 T
b10 d
b10 t
1&
1,
b101110 *
#485
0&
0,
#490
02
b101110 0
b11 3
b11 #
b11 5
b11 D
b11 T
b11 d
b11 t
b101101 E
b10 L
b11 K
b0 J
b11 I
b101101 B
1(
1.
1&
1,
b101111 *
#495
0&
0,
#500
b101110 B
b101110 E
b11 L
b10 K
b11 J
b0 I
11
b101111 0
b11 3
0(
0.
1&
1,
b110000 *
#505
0&
0,
#510
12
01
b110000 0
b10 3
b10 #
b10 5
b10 D
b10 T
b10 d
b10 t
b101111 E
b0 K
b10 I
b101111 B
1&
1,
b110001 *
#515
0&
0,
#520
b110000 B
b110000 E
b10 L
b11 K
b0 J
b11 I
02
b110001 0
b11 3
b11 #
b11 5
b11 D
b11 T
b11 d
b11 t
1(
1.
1&
1,
b110010 *
#525
0&
0,
#530
11
b110010 0
b11 3
b110001 E
b11 L
b10 K
b11 J
b0 I
b110001 B
0(
0.
1&
1,
b110011 *
#535
0&
0,
#540
b110010 B
b110010 E
b0 K
b10 I
12
01
b110011 0
b10 3
b10 #
b10 5
b10 D
b10 T
b10 d
b10 t
1(
1.
1&
1,
b110100 *
#545
0&
0,
#550
02
11
b110100 0
b0 #
b0 5
b0 D
b0 T
b0 d
b0 t
b0 3
b110011 E
b10 L
b11 K
b0 J
b11 I
b110011 B
0(
0.
1&
1,
b110101 *
#555
0&
0,
#560
b110100 B
b110100 E
b11 L
b0 K
b11 J
b10 I
12
01
b110101 0
b10 #
b10 5
b10 D
b10 T
b10 d
b10 t
b10 3
1&
1,
b110110 *
#565
0&
0,
#570
02
b110110 0
b11 3
b11 #
b11 5
b11 D
b11 T
b11 d
b11 t
b110101 E
b10 L
b11 K
b0 J
b11 I
b110101 B
1&
1,
b110111 *
#575
0&
0,
#580
b110110 B
b110110 E
b11 L
b10 K
b11 J
b0 I
b110111 0
b0 3
b0 #
b0 5
b0 D
b0 T
b0 d
b0 t
1(
1.
1&
1,
b111000 *
#585
0&
0,
#590
11
b111000 0
b11 3
b11 #
b11 5
b11 D
b11 T
b11 d
b11 t
b110111 E
b110111 B
0(
0.
1&
1,
b111001 *
#595
0&
0,
#600
b111000 B
b111000 E
b0 K
b10 I
12
01
b111001 0
b10 3
b10 #
b10 5
b10 D
b10 T
b10 d
b10 t
1&
1,
b111010 *
#605
0&
0,
#610
02
b111010 0
b11 3
b11 #
b11 5
b11 D
b11 T
b11 d
b11 t
b111001 E
b10 L
b11 K
b0 J
b11 I
b111001 B
1(
1.
1&
1,
b111011 *
#615
0&
0,
#620
b111010 B
b111010 E
b11 L
b10 K
b11 J
b0 I
11
b111011 0
b11 3
0(
0.
1&
1,
b111100 *
#625
0&
0,
#630
12
01
b111100 0
b10 3
b10 #
b10 5
b10 D
b10 T
b10 d
b10 t
b111011 E
b0 K
b10 I
b111011 B
1&
1,
b111101 *
#635
0&
0,
#640
b111100 B
b111100 E
b10 L
b11 K
b0 J
b11 I
02
b111101 0
b11 3
b11 #
b11 5
b11 D
b11 T
b11 d
b11 t
1(
1.
1&
1,
b111110 *
#645
0&
0,
#650
11
b111110 0
b11 3
b111101 E
b11 L
b10 K
b11 J
b0 I
b111101 B
0(
0.
1&
1,
b111111 *
#655
0&
0,
#660
b111110 B
b111110 E
b0 K
b10 I
12
01
b111111 0
b10 3
b10 #
b10 5
b10 D
b10 T
b10 d
b10 t
1&
1,
b1000000 *
#665
0&
0,
#670
02
b0 0
b11 3
b11 #
b11 5
b11 D
b11 T
b11 d
b11 t
b111111 E
b10 L
b11 K
b0 J
b11 I
b111111 B
0+
0/
1&
1,
b0 )
b0 *
#675
0&
0,
